{
    "openapi": "3.1.0",
    "info": {
        "title": "CoreBridge - resume-service",
        "description": "CoreBridge MSA - resume-service API \uba85\uc138",
        "version": "1.0.0"
    },
    "servers": [
        {
            "url": "http://localhost:8008",
            "description": "Generated server url"
        }
    ],
    "paths": {
        "/api/v1/resumes/me": {
            "get": {
                "tags": [
                    "resume-controller"
                ],
                "operationId": "getMyResume",
                "responses": {
                    "200": {
                        "description": "OK",
                        "content": {
                            "*/*": {
                                "schema": {
                                    "$ref": "#/components/schemas/BaseResponseResumeResponse"
                                }
                            }
                        }
                    }
                }
            },
            "put": {
                "tags": [
                    "resume-controller"
                ],
                "operationId": "updateMyResume",
                "requestBody": {
                    "content": {
                        "application/json": {
                            "schema": {
                                "$ref": "#/components/schemas/UpdateRequest"
                            }
                        }
                    },
                    "required": true
                },
                "responses": {
                    "200": {
                        "description": "OK",
                        "content": {
                            "*/*": {
                                "schema": {
                                    "$ref": "#/components/schemas/BaseResponseResumeResponse"
                                }
                            }
                        }
                    }
                }
            }
        },
        "/api/v1/resumes/{resumeId}/ai-result": {
            "post": {
                "tags": [
                    "resume-controller"
                ],
                "operationId": "updateAiResult",
                "parameters": [
                    {
                        "name": "resumeId",
                        "in": "path",
                        "required": true,
                        "schema": {
                            "type": "integer",
                            "format": "int64"
                        }
                    }
                ],
                "requestBody": {
                    "content": {
                        "application/json": {
                            "schema": {
                                "$ref": "#/components/schemas/AiResultRequest"
                            }
                        }
                    },
                    "required": true
                },
                "responses": {
                    "200": {
                        "description": "OK",
                        "content": {
                            "*/*": {
                                "schema": {
                                    "$ref": "#/components/schemas/BaseResponseResumeResponse"
                                }
                            }
                        }
                    }
                }
            }
        },
        "/api/v1/resumes/me/versions/{version}/restore": {
            "post": {
                "tags": [
                    "resume-controller"
                ],
                "operationId": "restoreVersion",
                "parameters": [
                    {
                        "name": "version",
                        "in": "path",
                        "required": true,
                        "schema": {
                            "type": "integer",
                            "format": "int32"
                        }
                    }
                ],
                "responses": {
                    "200": {
                        "description": "OK",
                        "content": {
                            "*/*": {
                                "schema": {
                                    "$ref": "#/components/schemas/BaseResponseResumeResponse"
                                }
                            }
                        }
                    }
                }
            }
        },
        "/api/v1/resumes/me/analyze": {
            "post": {
                "tags": [
                    "resume-controller"
                ],
                "operationId": "requestAnalysis",
                "responses": {
                    "200": {
                        "description": "OK",
                        "content": {
                            "*/*": {
                                "schema": {
                                    "$ref": "#/components/schemas/BaseResponseResumeResponse"
                                }
                            }
                        }
                    }
                }
            }
        },
        "/api/v1/resumes/me/versions": {
            "get": {
                "tags": [
                    "resume-controller"
                ],
                "operationId": "getVersions",
                "responses": {
                    "200": {
                        "description": "OK",
                        "content": {
                            "*/*": {
                                "schema": {
                                    "$ref": "#/components/schemas/BaseResponseVersionListResponse"
                                }
                            }
                        }
                    }
                }
            }
        },
        "/api/v1/resumes/me/versions/{version}": {
            "get": {
                "tags": [
                    "resume-controller"
                ],
                "operationId": "getVersion",
                "parameters": [
                    {
                        "name": "version",
                        "in": "path",
                        "required": true,
                        "schema": {
                            "type": "integer",
                            "format": "int32"
                        }
                    }
                ],
                "responses": {
                    "200": {
                        "description": "OK",
                        "content": {
                            "*/*": {
                                "schema": {
                                    "$ref": "#/components/schemas/BaseResponseVersionResponse"
                                }
                            }
                        }
                    }
                }
            }
        },
        "/api/v1/resumes/by-user/{userId}": {
            "get": {
                "tags": [
                    "resume-controller"
                ],
                "operationId": "getByUserId",
                "parameters": [
                    {
                        "name": "userId",
                        "in": "path",
                        "required": true,
                        "schema": {
                            "type": "integer",
                            "format": "int64"
                        }
                    }
                ],
                "responses": {
                    "200": {
                        "description": "OK",
                        "content": {
                            "*/*": {
                                "schema": {
                                    "$ref": "#/components/schemas/BaseResponseResumeResponse"
                                }
                            }
                        }
                    }
                }
            }
        }
    },
    "components": {
        "schemas": {
            "UpdateRequest": {
                "type": "object",
                "properties": {
                    "title": {
                        "type": "string"
                    },
                    "content": {
                        "type": "string"
                    },
                    "memo": {
                        "type": "string"
                    },
                    "skills": {
                        "type": "array",
                        "items": {
                            "type": "string"
                        }
                    }
                }
            },
            "BaseResponseResumeResponse": {
                "type": "object",
                "properties": {
                    "code": {
                        "type": "integer",
                        "format": "int32"
                    },
                    "message": {
                        "type": "string"
                    },
                    "result": {
                        "$ref": "#/components/schemas/ResumeResponse"
                    },
                    "success": {
                        "type": "boolean"
                    }
                }
            },
            "ResumeResponse": {
                "type": "object",
                "properties": {
                    "resumeId": {
                        "type": "integer",
                        "format": "int64"
                    },
                    "userId": {
                        "type": "integer",
                        "format": "int64"
                    },
                    "title": {
                        "type": "string"
                    },
                    "content": {
                        "type": "string"
                    },
                    "status": {
                        "type": "string",
                        "enum": [
                            "DRAFT",
                            "UPLOADED",
                            "ANALYZING",
                            "ANALYZED",
                            "FAILED",
                            "ACTIVE",
                            "DELETED"
                        ]
                    },
                    "currentVersion": {
                        "type": "integer",
                        "format": "int32"
                    },
                    "createdAt": {
                        "type": "string",
                        "format": "date-time"
                    },
                    "updatedAt": {
                        "type": "string",
                        "format": "date-time"
                    },
                    "skills": {
                        "type": "array",
                        "items": {
                            "type": "string"
                        }
                    },
                    "aiSummary": {
                        "type": "string"
                    },
                    "aiSkills": {
                        "type": "array",
                        "items": {
                            "type": "string"
                        }
                    },
                    "analyzedAt": {
                        "type": "string",
                        "format": "date-time"
                    }
                }
            },
            "AiResultRequest": {
                "type": "object",
                "properties": {
                    "summary": {
                        "type": "string"
                    },
                    "skills": {
                        "type": "string"
                    }
                }
            },
            "BaseResponseVersionListResponse": {
                "type": "object",
                "properties": {
                    "code": {
                        "type": "integer",
                        "format": "int32"
                    },
                    "message": {
                        "type": "string"
                    },
                    "result": {
                        "$ref": "#/components/schemas/VersionListResponse"
                    },
                    "success": {
                        "type": "boolean"
                    }
                }
            },
            "VersionListResponse": {
                "type": "object",
                "properties": {
                    "versions": {
                        "type": "array",
                        "items": {
                            "$ref": "#/components/schemas/VersionResponse"
                        }
                    },
                    "totalCount": {
                        "type": "integer",
                        "format": "int32"
                    }
                }
            },
            "VersionResponse": {
                "type": "object",
                "properties": {
                    "versionId": {
                        "type": "integer",
                        "format": "int64"
                    },
                    "resumeId": {
                        "type": "integer",
                        "format": "int64"
                    },
                    "version": {
                        "type": "integer",
                        "format": "int32"
                    },
                    "title": {
                        "type": "string"
                    },
                    "content": {
                        "type": "string"
                    },
                    "memo": {
                        "type": "string"
                    },
                    "createdAt": {
                        "type": "string",
                        "format": "date-time"
                    }
                }
            },
            "BaseResponseVersionResponse": {
                "type": "object",
                "properties": {
                    "code": {
                        "type": "integer",
                        "format": "int32"
                    },
                    "message": {
                        "type": "string"
                    },
                    "result": {
                        "$ref": "#/components/schemas/VersionResponse"
                    },
                    "success": {
                        "type": "boolean"
                    }
                }
            }
        }
    }
}
